pyaishortcuts/__init__.py
pyaishortcuts/__main__.py
pyaishortcuts/ai_processor.py
pyaishortcuts/main.py
pyaishortcuts-0.1.1.dist-info/METADATA
pyaishortcuts-0.1.1.dist-info/WHEEL
pyaishortcuts-0.1.1.dist-info/entry_points.txt
pyaishortcuts-0.1.1.dist-info/top_level.txt
pyaishortcuts-0.1.1.dist-info/RECORD
