Metadata-Version: 2.4
Name: pyaishortcuts
Version: 0.1.1
Summary: lightweight/neat shortcuts to access llm for daily does, like email assistance, translation
Project-URL: Homepage, https://github.com/fxyzbtc/aishortcuts
Project-URL: Issues, https://github.com/fxyzbtc/aishortcuts/issues
Requires-Python: >=3.12
Requires-Dist: loguru>=0.7.3
Requires-Dist: openai>=1.70.0
Requires-Dist: pyperclip>=1.9.0
Requires-Dist: freesimplegui>=5.0.8.3
Requires-Dist: python-dotenv>=1.1.0
Requires-Dist: requests>=2.32.3
